beep_lite/__init__.py
beep_lite/api.py
beep_lite/core.py
beep_lite/loader.py
beep_lite/types.py
beep_lite/assets/__init__.py
beep_lite/assets/crit.wav
beep_lite/assets/mew.wav
beep_lite/assets/moo.wav
beep_lite/assets/ng.wav
beep_lite/assets/ok.wav
beep_lite/assets/scan_ng.wav
beep_lite/assets/scan_ok.wav
beep_lite/assets/warn.wav
beep_lite/backends/__init__.py
beep_lite/backends/fallback_backend.py
beep_lite/backends/simpleaudio_backend.py
beep_lite/backends/winsound_backend.py
beep_lite-0.1.2.dist-info/METADATA
beep_lite-0.1.2.dist-info/WHEEL
beep_lite-0.1.2.dist-info/licenses/LICENSE
beep_lite-0.1.2.dist-info/RECORD
