Metadata-Version: 2.4
Name: beep-lite
Version: 0.1.2
Summary: Cross-platform notification sound library - lightweight and easy to use
Project-URL: Homepage, https://github.com/Moge800/beep_lite
Project-URL: Repository, https://github.com/Moge800/beep_lite
Project-URL: Documentation, https://github.com/Moge800/beep_lite#readme
Author: Moge800
License: MIT
License-File: LICENSE
Keywords: audio,beep,cross-platform,lite,notification,sound
Classifier: Development Status :: 3 - Alpha
Classifier: Intended Audience :: Developers
Classifier: License :: OSI Approved :: MIT License
Classifier: Operating System :: OS Independent
Classifier: Programming Language :: Python :: 3
Classifier: Programming Language :: Python :: 3.10
Classifier: Programming Language :: Python :: 3.11
Classifier: Programming Language :: Python :: 3.12
Classifier: Programming Language :: Python :: 3.13
Classifier: Topic :: Multimedia :: Sound/Audio
Classifier: Typing :: Typed
Requires-Python: >=3.10
Provides-Extra: audio
Requires-Dist: simpleaudio>=1.0.4; extra == 'audio'
Provides-Extra: dev
Requires-Dist: black>=24.0.0; extra == 'dev'
Requires-Dist: pytest-cov>=4.0.0; extra == 'dev'
Requires-Dist: pytest>=8.0.0; extra == 'dev'
Requires-Dist: ruff>=0.1.0; extra == 'dev'
Requires-Dist: ty>=0.0.1a7; extra == 'dev'
